lulkrypt.py
lulkrypt-0.1.0.dist-info/DESCRIPTION.rst
lulkrypt-0.1.0.dist-info/METADATA
lulkrypt-0.1.0.dist-info/RECORD
lulkrypt-0.1.0.dist-info/WHEEL
lulkrypt-0.1.0.dist-info/entry_points.txt
lulkrypt-0.1.0.dist-info/metadata.json
lulkrypt-0.1.0.dist-info/top_level.txt
