Metadata-Version: 2.0
Name: lulkrypt
Version: 0.1.0
Summary: An incredibly useful script that encrypts and decrypts ASCII strings.
Home-page: UNKNOWN
Author: Hadrian Black
Author-email: lolroflomg303@gmail.com
License: UNKNOWN
Platform: UNKNOWN
